Modules/ALU.v
`timescale 1ns / 1ps
module ALU(input  [31:0]SrcAE,
           input  [31:0]SrcBE,
           input  [2:0]ALUControlE,
           output ZeroE,
           output reg [31:0]ALUResultE);

	always @(*)
	    case (ALUControlE)
		0: ALUResultE = SrcAE + SrcBE;
		1: ALUResultE = SrcAE - SrcBE;
		2: ALUResultE = SrcAE & SrcBE;
		3: ALUResultE = SrcAE | SrcBE;
		4: ALUResultE = SrcAE > SrcBE;
		5: ALUResultE = SrcAE < SrcBE;
		6: ALUResultE = SrcAE ^ SrcBE;
		7: ALUResultE = SrcAE == SrcBE;
		default: ALUResultE = 32'd0;
	    endcase

	assign ZeroE = SrcAE==SrcBE;

endmodule

Testbench/ALU_tb.v
`timescale 1 ns/1 ps

module ALU_tb;
	reg [31:0] SrcAE;
	reg [31:0] SrcBE;
	reg [2:0] ALUControlE;
	wire ZeroE;
	wire [31:0] ALUResultE;
	reg clock = 0;

	ALU u1 (
		.SrcAE(SrcAE),
		.SrcBE(SrcBE),
		.ALUControlE(ALUControlE),
		.ZeroE(ZeroE),
		.ALUResultE(ALUResultE)
	);

	parameter CLOCK_PERIOD = 10;
	always begin
       		#(CLOCK_PERIOD/2);
		clock = ~clock;
	end

	initial	begin
		SrcAE = 32'd6;
		SrcBE = 32'd3;
		ALUControlE = 3'd0;
		#(CLOCK_PERIOD*5);
		ALUControlE = 3'd1;
		#(CLOCK_PERIOD*5);
		ALUControlE = 3'd2;
		#(CLOCK_PERIOD*5);
		ALUControlE = 3'd3;
		#(CLOCK_PERIOD*5);
		ALUControlE = 3'd4;
		#(CLOCK_PERIOD*5);
		ALUControlE = 3'd5;
		#(CLOCK_PERIOD*5);
		ALUControlE = 3'd6;
		#(CLOCK_PERIOD*5);
		ALUControlE = 3'd7;
		#(CLOCK_PERIOD*5);
	end

	initial begin
		$dumpfile("out.vcd");
		$dumpvars;
		#(1000);
		$finish;
	end
endmodule

Testbench/out.vcd
$date
	Sun Oct 20 17:22:47 2024
$end
$version
	Icarus Verilog
$end
$timescale
	1ps
$end
$scope module ALU_tb $end
$var wire 1 ! ZeroE $end
$var wire 32 " ALUResultE [31:0] $end
$var reg 3 # ALUControlE [2:0] $end
$var reg 32 $ SrcAE [31:0] $end
$var reg 32 % SrcBE [31:0] $end
$var reg 1 & clock $end
$scope module u1 $end
$var wire 3 ' ALUControlE [2:0] $end
$var wire 32 ( SrcAE [31:0] $end
$var wire 32 ) SrcBE [31:0] $end
$var wire 1 ! ZeroE $end
$var reg 32 * ALUResultE [31:0] $end
$upscope $end
$upscope $end
$enddefinitions $end
#0
$dumpvars
b1001 *
b11 )
b110 (
b0 '
0&
b11 %
b110 $
b0 #
b1001 "
0!
$end
#5000
1&
#10000
0&
#15000
1&
#20000
0&
#25000
1&
#30000
0&
#35000
1&
#40000
0&
#45000
1&
#50000
b11 "
b11 *
0&
b1 #
b1 '
#55000
1&
#60000
0&
#65000
1&
#70000
0&
#75000
1&
#80000
0&
#85000
1&
#90000
0&
#95000
1&
#100000
b10 "
b10 *
0&
b10 #
b10 '
#105000
1&
#110000
0&
#115000
1&
#120000
0&
#125000
1&
#130000
0&
#135000
1&
#140000
0&
#145000
1&
#150000
b111 "
b111 *
0&
b11 #
b11 '
#155000
1&
#160000
0&
#165000
1&
#170000
0&
#175000
1&
#180000
0&
#185000
1&
#190000
0&
#195000
1&
#200000
b1 "
b1 *
0&
b100 #
b100 '
#205000
1&
#210000
0&
#215000
1&
#220000
0&
#225000
1&
#230000
0&
#235000
1&
#240000
0&
#245000
1&
#250000
b0 "
b0 *
0&
b101 #
b101 '
#255000
1&
#260000
0&
#265000
1&
#270000
0&
#275000
1&
#280000
0&
#285000
1&
#290000
0&
#295000
1&
#300000
b101 "
b101 *
0&
b110 #
b110 '
#305000
1&
#310000
0&
#315000
1&
#320000
0&
#325000
1&
#330000
0&
#335000
1&
#340000
0&
#345000
1&
#350000
b0 "
b0 *
0&
b111 #
b111 '
